shotstriper/__init__.py
shotstriper/main.py
shotstriper/palettes.py
shotstriper-0.2.1.dist-info/entry_points.txt
shotstriper-0.2.1.dist-info/WHEEL
shotstriper-0.2.1.dist-info/LICENSE
shotstriper-0.2.1.dist-info/METADATA
shotstriper-0.2.1.dist-info/RECORD
