Metadata-Version: 2.1
Name: shotstriper
Version: 0.2.1
Summary: Add beautiful, striped backgrounds to your screenshots
Home-page: https://github.com/psyonara/shotstriper
Author: Helmut Irle
Author-email: me@helmut.dev
Requires-Python: >=3.10,<4.0
Classifier: Programming Language :: Python :: 3
Classifier: Programming Language :: Python :: 3.10
Classifier: Programming Language :: Python :: 3.11
Requires-Dist: aggdraw (>=1.3.18.post0,<2.0.0)
Requires-Dist: pillow (>=10.2.0,<11.0.0)
Requires-Dist: typer[all] (>=0.10.0,<0.11.0)
